[
    {"id": 1, "region": "AF", "data": 250},
    {"id": 2, "region": "AL", "data": 320},
    {"id": 3, "region": "DZ", "data": 480},
    {"id": 4, "region": "AI", "data": 280},
    {"id": 5, "region": "AM", "data": 620},
    {"id": 6, "region": "AW", "data": 410},
    {"id": 7, "region": "AT", "data": 750},
    {"id": 8, "region": "BH", "data": 380},
    {"id": 9, "region": "BD", "data": 510},
    {"id": 10, "region": "BB", "data": 470},
    {"id": 11, "region": "BY", "data": 340},
    {"id": 12, "region": "BE", "data": 610},
    {"id": 13, "region": "BZ", "data": 490},
    {"id": 14, "region": "BJ", "data": 390},
    {"id": 15, "region": "BM", "data": 580},
    {"id": 16, "region": "BT", "data": 430},
    {"id": 17, "region": "BO", "data": 520},
    {"id": 18, "region": "BA", "data": 690},
    {"id": 19, "region": "BW", "data": 460},
    {"id": 20, "region": "BR", "data": 670},
    {"id": 21, "region": "VG", "data": 720},
    {"id": 22, "region": "BN", "data": 580},
    {"id": 23, "region": "BG", "data": 510},
    {"id": 24, "region": "BF", "data": 390},
    {"id": 25, "region": "BI", "data": 460},
    {"id": 26, "region": "KH", "data": 380},
    {"id": 27, "region": "CM", "data": 600},
    {"id": 28, "region": "CF", "data": 520},
    {"id": 29, "region": "TD", "data": 470},
    {"id": 30, "region": "CO", "data": 690},
    {"id": 31, "region": "CR", "data": 420},
    {"id": 32, "region": "HR", "data": 350},
    {"id": 33, "region": "CU", "data": 680},
    {"id": 34, "region": "CW", "data": 650},
    {"id": 35, "region": "CZ", "data": 590},
    {"id": 36, "region": "CI", "data": 530},
    {"id": 37, "region": "KP", "data": 480},
    {"id": 38, "region": "CD", "data": 470},
    {"id": 39, "region": "DJ", "data": 690},
    {"id": 40, "region": "DM", "data": 610},
    {"id": 41, "region": "DO", "data": 580},
    {"id": 42, "region": "EC", "data": 390},
    {"id": 43, "region": "EG", "data": 410},
    {"id": 44, "region": "SV", "data": 570},
    {"id": 45, "region": "GQ", "data": 670},
    {"id": 46, "region": "ER", "data": 540},
    {"id": 47, "region": "EE", "data": 650},
    {"id": 48, "region": "ET", "data": 480},
    {"id": 49, "region": "FI", "data": 430},
    {"id": 50, "region": "GF", "data": 460},
    {"id": 51, "region": "GA", "data": 600},
    {"id": 52, "region": "GE", "data": 330},
    {"id": 53, "region": "DE", "data": 510},
    {"id": 54, "region": "GH", "data": 470},
    {"id": 55, "region": "GL", "data": 360},
    {"id": 56, "region": "GD", "data": 420},
    {"id": 57, "region": "GU", "data": 550},
    {"id": 58, "region": "GT", "data": 670},
    {"id": 59, "region": "GN", "data": 340},
    {"id": 60, "region": "GW", "data": 510},
    {"id": 61, "region": "GY", "data": 460},
    {"id": 62, "region": "HT", "data": 650},
    {"id": 63, "region": "HN", "data": 500},
    {"id": 64, "region": "HU", "data": 680},
    {"id": 65, "region": "IS", "data": 520},
    {"id": 66, "region": "IN", "data": 410},
    {"id": 67, "region": "IR", "data": 490},
    {"id": 68, "region": "IQ", "data": 340},
    {"id": 69, "region": "IE", "data": 420},
    {"id": 70, "region": "IL", "data": 540},
    {"id": 71, "region": "JM", "data": 590},
    {"id": 72, "region": "JO", "data": 470},
    {"id": 73, "region": "KZ", "data": 460},
    {"id": 74, "region": "KE", "data": 500},
    {"id": 75, "region": "XK", "data": 630},
    {"id": 76, "region": "KW", "data": 370},
    {"id": 77, "region": "KG", "data": 690},
    {"id": 78, "region": "LA", "data": 380},
    {"id": 79, "region": "LV", "data": 350},
    {"id": 80, "region": "LB", "data": 610},
    {"id": 81, "region": "LS", "data": 540},
    {"id": 82, "region": "LR", "data": 430},
    {"id": 83, "region": "LY", "data": 470},
    {"id": 84, "region": "LT", "data": 660},
    {"id": 85, "region": "LU", "data": 520},
    {"id": 86, "region": "MK", "data": 420},
    {"id": 87, "region": "MG", "data": 670},
    {"id": 88, "region": "MW", "data": 460},
    {"id": 89, "region": "MV", "data": 510},
    {"id": 90, "region": "ML", "data": 480},
    {"id": 91, "region": "MH", "data": 340},
    {"id": 92, "region": "MQ", "data": 330},
    {"id": 93, "region": "MR", "data": 620},
    {"id": 94, "region": "YT", "data": 380},
    {"id": 95, "region": "MX", "data": 420},
    {"id": 96, "region": "MD", "data": 670},
    {"id": 97, "region": "MN", "data": 480},
    {"id": 98, "region": "ME", "data": 570},
    {"id": 99, "region": "MS", "data": 690},
    {"id": 100, "region": "MA", "data": 520},
    {"id": 101, "region": "MZ", "data": 590},
    {"id": 102, "region": "MM", "data": 440},
    {"id": 103, "region": "NA", "data": 470},
    {"id": 104, "region": "NR", "data": 600},
    {"id": 105, "region": "NP", "data": 350},
    {"id": 106, "region": "NL", "data": 460},
    {"id": 107, "region": "BQBO", "data": 200},
    {"id": 108, "region": "NI", "data": 560},
    {"id": 109, "region": "NE", "data": 590},
    {"id": 110, "region": "NG", "data": 420},
    {"id": 111, "region": "PK", "data": 190},
    {"id": 112, "region": "PW", "data": 430},
    {"id": 113, "region": "PS", "data": 540},
    {"id": 114, "region": "PA", "data": 580},
    {"id": 115, "region": "PY", "data": 480},
    {"id": 116, "region": "PE", "data": 570},
    {"id": 117, "region": "PL", "data": 620},
    {"id": 118, "region": "PT", "data": 680},
    {"id": 119, "region": "QA", "data": 430},
    {"id": 120, "region": "CG", "data": 530},
    {"id": 121, "region": "KR", "data": 620},
    {"id": 122, "region": "RE", "data": 410},
    {"id": 123, "region": "RO", "data": 530},
    {"id": 124, "region": "RW", "data": 550},
    {"id": 125, "region": "BQSA", "data": 450},
    {"id": 126, "region": "LC", "data": 570},
    {"id": 127, "region": "VC", "data": 380},
    {"id": 128, "region": "BL", "data": 340},
    {"id": 129, "region": "MF", "data": 430},
    {"id": 130, "region": "SA", "data": 550},
    {"id": 131, "region": "SN", "data": 320},
    {"id": 132, "region": "RS", "data": 480},
    {"id": 133, "region": "SL", "data": 280},
    {"id": 134, "region": "SX", "data": 620},
    {"id": 135, "region": "SK", "data": 410},
    {"id": 136, "region": "SI", "data": 750},
    {"id": 137, "region": "SO", "data": 420},
    {"id": 138, "region": "ZA", "data": 690},
    {"id": 139, "region": "SS", "data": 280},
    {"id": 140, "region": "ES", "data": 820},
    {"id": 141, "region": "LK", "data": 470},
    {"id": 142, "region": "BQSE", "data": 380},
    {"id": 143, "region": "SD", "data": 570},
    {"id": 144, "region": "SR", "data": 340},
    {"id": 145, "region": "SZ", "data": 460},
    {"id": 146, "region": "SE", "data": 710},
    {"id": 147, "region": "CH", "data": 680},
    {"id": 148, "region": "SY", "data": 480},
    {"id": 149, "region": "TW", "data": 540},
    {"id": 150, "region": "TJ", "data": 640},
    {"id": 151, "region": "TZ", "data": 520},
    {"id": 152, "region": "TH", "data": 750},
    {"id": 153, "region": "GM", "data": 390},
    {"id": 154, "region": "TL", "data": 480},
    {"id": 155, "region": "TG", "data": 320},
    {"id": 156, "region": "TN", "data": 600},
    {"id": 157, "region": "TM", "data": 440},
    {"id": 158, "region": "TV", "data": 370},
    {"id": 159, "region": "UG", "data": 510},
    {"id": 160, "region": "UA", "data": 680},
    {"id": 161, "region": "AE", "data": 790},
    {"id": 162, "region": "UY", "data": 520},
    {"id": 163, "region": "UZ", "data": 610},
    {"id": 164, "region": "VE", "data": 500},
    {"id": 165, "region": "VN", "data": 600},
    {"id": 166, "region": "EH", "data": 350},
    {"id": 167, "region": "YE", "data": 450},
    {"id": 168, "region": "ZM", "data": 520},
    {"id": 169, "region": "ZW", "data": 430}
]